fundspy
