Metadata-Version: 2.1
Name: fundspy
Version: 0.1.4
Summary: Download brazillian investment funds and their benchmarks data from CVM and analyze them with pre-built functions. 
Home-page: https://linktr.ee/joaopenido
Author: Joao Penido Monteiro
Author-email: joaopm33@gmail.com
License: MIT
Download-URL: https://github.com/joaopm33/fundspy/archive/refs/tags/v0.1.tar.gz
Keywords: SOME,MEANINGFULL,KEYWORDS
Platform: UNKNOWN
Classifier: Development Status :: 4 - Beta
Classifier: Intended Audience :: Developers
Classifier: Intended Audience :: Education
Classifier: Intended Audience :: Financial and Insurance Industry
Classifier: Topic :: Office/Business :: Financial :: Investment
Classifier: License :: OSI Approved :: MIT License
Classifier: Programming Language :: Python :: 3
Classifier: Programming Language :: Python :: 3.4
Classifier: Programming Language :: Python :: 3.5
Classifier: Programming Language :: Python :: 3.6
Classifier: Programming Language :: Python :: 3.7
Classifier: Programming Language :: Python :: 3.8
